commons_lang_util/__init__.py
commons_lang_util/file_util.py
commons_lang_util/os_util.py
commons_lang_util/string_util.py
commons_lang_util-0.1.6.dist-info/METADATA
commons_lang_util-0.1.6.dist-info/WHEEL
commons_lang_util-0.1.6.dist-info/top_level.txt
commons_lang_util-0.1.6.dist-info/RECORD
